{
"parent": "nitwit_trades:plains/warped_wart_block",
"display": {
	"icon": { "item": "minecraft:soul_sand" },
	"title": { "translate": "block.minecraft.soul_sand" },
	"description": "",
	"frame": "task",
	"announce_to_chat": false,
	"show_toast": true
},
"criteria": {
	"nitwit_trades:soul_sand": {
		"trigger": "minecraft:inventory_changed",
		"conditions": {
			"items": [
				{
				"item": "minecraft:player_head",
				"nbt": "{ SkullOwner: { Id: [I; -1538066674, -2048701192, -1339165068, -775416280], Properties: { textures: [ { Value: 'eyJ0ZXh0dXJlcyI6eyJTS0lOIjp7InVybCI6Imh0dHA6Ly90ZXh0dXJlcy5taW5lY3JhZnQubmV0L3RleHR1cmUvYTg3MDk1ZmFmMzMxNzgzMTJmNjEyOGI5Y2Q0YWZjNTIzMGRiNjA5Y2I2Mzk2M2ZmYmRlYmVmOTQ4MTdiMzM3MyJ9fX0=' } ] } } }"
				}
			]
		}
	}
}
}